{
    "DataType": "CustomerData",
    "DataVersion": 0,
    "GameVersion": "0.3.4f4",
    "Dependence": 0.06800000369548798,
    "PurchaseableProducts": [
        "greencrack",
        "sourdiesel",
        "pinkcheese",
        "granddaddypurple",
        "ogkush",
        "weddingass"
    ],
    "ProductAffinities": [
        -0.775506854057312,
        0.418253630399704,
        0.6501095294952393
    ],
    "TimeSinceLastDealCompleted": 2766,
    "TimeSinceLastDealOffered": 3937,
    "OfferedDeals": 1,
    "CompletedDeals": 1,
    "IsContractOffered": false,
    "OfferedContract": {
        "Payment": 0.0,
        "Products": {
            "entries": []
        },
        "DeliveryLocationGUID": "",
        "DeliveryWindow": {
            "IsEnabled": false,
            "WindowStartTime": 1200,
            "WindowEndTime": 1800
        },
        "Expires": false,
        "ExpiresAfter": 0,
        "PickupScheduleIndex": 0,
        "IsCounterOffer": false
    },
    "OfferedContractTime": {
        "elapsedDays": 0,
        "time": 0
    },
    "TimeSincePlayerApproached": 1037865,
    "TimeSinceInstantDealOffered": 1037865,
    "HasBeenRecommended": false
}